Workbook

Sheet Lisez-moi
A1: Cas pratique - Pilotage d'un portefeuille de produits digitaux
A2: Données synthétiques
A4: Contexte
A5: La direction générale suit 10 produits digitaux. Vous êtes analyste au PMO : chaque mois, vous devez dire quels produits avancent, lesquels dérapent, et où agir.
A6: Date de situation : 31/08/2026. Montants en millions de FCFA.
A8: Tables
A9: • Projets : fiche d'identité de chaque produit (budget, dates, priorité).
A10: • Jalons : 5 étapes par produit, dates prévues et réelles/estimées.
A11: • Suivi_mensuel : avancement prévu et réel (cumulés, en %) et dépenses cumulées, fin de chaque mois.
A12: • Risques : registre des risques avec probabilité et impact (échelle 1 à 3).
A13: • KPIs_produit : adoption des produits déjà lancés, cible vs réel.
A15: Calcul
... A19: 4. Retard des jalons en jours et criticité des risques (probabilité × impact).

Sheet Projets
A1: Code | B1: Produit | C1: Catégorie | D1: Direction porteuse | E1: Product Owner | F1: Date début | G1: Date fin prévue | H1: Budget (M FCFA) | I1: Priorité
A2: P01 | B2: Application mobile client V2 | C2: Acquisition | D2: Direction Digitale | E2: A. Mensah | F2: 45996 | G2: 46217 | H2: 420 | I2: P1
A3: P02 | B3: Portail self-service web | C3: Efficacité opérationnelle | D3: Direction Relation Client | E3: K. Adjo | F3: 46024 | G3: 46325 | H3: 260 | I3: P2
A4: P03 | B4: Programme de fidélité | C4: Revenus | D4: Direction Marketing | E4: S. Diallo | F4: 46003 | G4: 46234 | H4: 180 | I4: P1
A5: P04 | B5: Paiement marchand par QR code | C5: Revenus | D5: Direction Digitale | E5: Y. Kossi | F5: 46055 | G5: 46356 | H5: 350 | I5: P1
A6: P05 | B6: Chatbot service client | C6: Efficacité opérationnelle | D6: Direction Relation Client | E6: M. Traoré | F6: 46087 | G6: 46295 | H6: 120 | I6: P2
A7: P06 | B7: Migration du CRM | C7: Efficacité opérationnelle | D7: Direction SI | E7: E. Amegan | F7: 45996 | G7: 46344 | H7: 510 | I7: P1
A8: P07 | B8: Plateforme data (datalake) | C8: Data | D8: Direction SI | E8: F. Bamba | F8: 46038 | G8: 46446 | H8: 480 | I8: P2
A9: P08 | B9: Marketplace partenaires | C9: Revenus | D9: Direction Partenariats | E9: R. Agbeko | F9: 46116 | G9: 46413 | H9: 300 | I9: P2
A10: P09 | B10: Onboarding eKYC | C10: Acquisition | D10: Direction Digitale | E10: L. Sow | F10: 46003 | G10: 46172 | H10: 150 | I10: P1
A11: P10 | B11: Tableaux de bord BI de direction | C11: Data | D11: Direction Finance | E11: N. Kouassi | F11: 46143 | G11: 46341 | H11: 90 | I11: P3

Sheet Jalons
A1: Code produit | B1: ID jalon | C1: Jalon | D1: Date prévue | E1: Date réelle / estimée | F1: Statut | G1: Jalon critique
A2: P01 | B2: P01-J1 | C2: Cadrage | D2: 46014 | E2: 46017 | F2: Terminé | G2: Non
A3: P01 | B3: P01-J2 | C3: Conception | D3: 46054 | E3: 46056 | F3: Terminé | G3: Non
A4: P01 | B4: P01-J3 | C4: Développement | D4: 46141 | E4: 46149 | F4: Terminé | G4: Oui
A5: P01 | B5: P01-J4 | C5: Recette | D5: 46185 | E5: 46188 | F5: Terminé | G5: Non
A6: P01 | B6: P01-J5 | C6: Lancement | D6: 46217 | E6: 46221 | F6: Terminé | G6: Oui
A7: P02 | B7: P02-J1 | C7: Cadrage | D7: 46048 | E7: 46045 | F7: Terminé | G7: Non
A8: P02 | B8: P02-J2 | C8: Conception | D8: 46099 | E8: 46101 | F8: Terminé | G8: Non
A9: P02 | B9: P02-J3 | C9: Développement | D9: 46220 | E9: 46217 | F9: Terminé | G9: Oui
A10: P02 | B10: P02-J4 | C10: Recette | D10: 46281 | E10: 46281 | F10: En cours | G10: Non
A11: P02 | B11: P02-J5 | C11: Lancement | D11: 46325 | E11: 46322 | F11: À venir | G11: Oui
A12: P03 | B12: P03-J1 | C12: Cadrage | D12: 46021 | E12: 46025 | F12: Terminé | G12: Non
A13: P03 | B13: P03-J2 | C13: Conception | D13: 46064 | E13: 46088 | F13: Terminé | G13: Non
... A51: P10 | B51: P10-J5 | C51: Lancement | D51: 46341 | E51: 46336 | F51: À venir | G51: Oui

Sheet Suivi_mensuel
A1: Code produit | B1: Fin de mois | C1: Avancement prévu (cumulé) | D1: Avancement réel (cumulé) | E1: Dépenses cumulées (M FCFA)
A2: P01 | B2: 46022 | C2: 0.034 | D2: 0.033 | E2: 14.1
A3: P01 | B3: 46053 | C3: 0.14 | D3: 0.138 | E3: 59.5
A4: P01 | B4: 46081 | C4: 0.323 | D4: 0.311 | E4: 135.8
A5: P01 | B5: 46112 | C5: 0.532 | D5: 0.51 | E5: 217.8
A6: P01 | B6: 46142 | C6: 0.742 | D6: 0.725 | E6: 306.3
A7: P01 | B7: 46173 | C7: 0.901 | D7: 0.874 | E7: 367.4
A8: P01 | B8: 46203 | C8: 0.99 | D8: 0.965 | E8: 417.9
A9: P01 | B9: 46234 | C9: 1 | D9: 0.972 | E9: 422.7
A10: P01 | B10: 46265 | C10: 1 | D10: 0.965 | E10: 416.5
A11: P02 | B11: 46053 | C11: 0.018 | D11: 0.018 | E11: 4.7
A12: P02 | B12: 46081 | C12: 0.086 | D12: 0.086 | E12: 22.2
A13: P02 | B13: 46112 | C13: 0.192 | D13: 0.195 | E13: 49.6
... A75: P10 | B75: 46265 | C75: 0.676 | D75: 0.683 | E75: 60.8

Sheet Risques
A1: Code produit | B1: ID risque | C1: Description | D1: Probabilité (1-3) | E1: Impact (1-3) | F1: Responsable | G1: Action corrective | H1: Statut | I1: Échéance action
A2: P03 | B2: R01 | C2: Faible adhésion des partenaires commerciaux au programme | D2: 3 | E2: 3 | F2: Direction Marketing | G2: Relancer 5 partenaires clés avec offre co-marketing | H2: Ouvert | I2: 46249
A3: P03 | B3: R02 | C3: Dépassement du budget lié aux récompenses clients | D3: 2 | E3: 3 | F3: Direction Finance | G3: Plafonner les récompenses du trimestre 4 | H3: Ouvert | I3: 46280
A4: P06 | B4: R03 | C4: Qualité des données clients insuffisante pour la migration | D4: 3 | E4: 3 | F4: Direction SI | G4: Campagne de nettoyage des doublons avant bascule | H4: Ouvert | I4: 46254
A5: P06 | B5: R04 | C5: Indisponibilité de l'intégrateur externe | D5: 2 | E5: 3 | F5: Direction SI | G5: Négocier une équipe dédiée au contrat | H5: Ouvert | I5: 46270
A6: P06 | B6: R05 | C6: Résistance au changement des équipes commerciales | D6: 2 | E6: 2 | F6: Direction Commerciale | G6: Plan de formation et ambassadeurs internes | H6: En cours | I6: 46296
A7: P04 | B7: R06 | C7: Retard de validation réglementaire du paiement QR | D7: 3 | E7: 2 | F7: Direction Juridique | G7: Réunion d'arbitrage avec le régulateur | H7: Ouvert | I7: 46259
A8: P04 | B8: R07 | C8: Faible équipement des commerçants en smartphones | D8: 2 | E8: 2 | F8: Direction Partenariats | G8: Kit QR imprimé pour les commerçants | H8: En cours | I8: 46310
A9: P01 | B9: R08 | C9: Bugs critiques remontés en recette sur Android ancien | D9: 2 | E9: 2 | F9: Direction Digitale | G9: Sprint correctif dédié | H9: En cours | I9: 46275
A10: P02 | B10: R09 | C10: Charge serveur lors des pics de connexion | D10: 1 | E10: 3 | F10: Direction SI | G10: Test de charge avant mise en production | H10: Ouvert | I10: 46295
A11: P05 | B11: R10 | C11: Réponses du chatbot jugées imprécises | D11: 2 | E11: 1 | F11: Direction Relation Client | G11: Enrichir la base de questions fréquentes | H11: En cours | I11: 46285
A12: P07 | B12: R11 | C12: Montée en compétence de l'équipe data | D12: 2 | E12: 2 | F12: Direction SI | G12: Formation cloud pour 4 ingénieurs | H12: En cours | I12: 46327
A13: P07 | B13: R12 | C13: Sécurité et confidentialité des données | D13: 1 | E13: 3 | F13: Direction SI | G13: Audit sécurité avant ouverture | H13: Ouvert | I13: 46371
... A19: P06 | B19: R18 | C19: Double saisie pendant la période de transition | D19: 3 | E19: 1 | F19: Direction SI | G19: Limiter la transition à 2 semaines | H19: Ouvert | I19: 46327

Sheet KPIs_produit
A1: Code produit | B1: Produit | C1: Indicateur | D1: Mois | E1: Cible | F1: Réel
A2: P09 | B2: Onboarding eKYC | C2: Comptes ouverts en ligne / mois | D2: 46203 | E2: 12000 | F2: 8200
A3: P09 | B3: Onboarding eKYC | C3: Comptes ouverts en ligne / mois | D3: 46234 | E3: 12000 | F3: 10900
A4: P09 | B4: Onboarding eKYC | C4: Comptes ouverts en ligne / mois | D4: 46265 | E4: 12000 | F4: 12600
A5: P09 | B5: Onboarding eKYC | C5: Taux de validation automatique | D5: 46203 | E5: 0.85 | F5: 0.71
A6: P09 | B6: Onboarding eKYC | C6: Taux de validation automatique | D6: 46234 | E6: 0.85 | F6: 0.79
A7: P09 | B7: Onboarding eKYC | C7: Taux de validation automatique | D7: 46265 | E7: 0.85 | F7: 0.83
A8: P01 | B8: Application mobile client V2 | C8: Utilisateurs actifs mensuels | D8: 46265 | E8: 150000 | F8: 118000
A9: P01 | B9: Application mobile client V2 | C9: Note moyenne sur les stores | D9: 46265 | E9: 4.3 | F9: 3.9

Sheet Calcul
A1: 46265
A3: Code produit | B3: Avancement prévu | C3: Avancement réel (cumulé) | D3: Budget | E3: PV (valeur planifiée en M) | F3: EV ( valeur acquise en M) | G3: AC (coûts réels) | H3: SPI (Indice de performance des délais) | I3: CPI (Indice de performance des coûts) | J3: EAC ( estimation de coût final) | K3: VAC ( Ecart prévu à la fin ) | L3: Statut
A4: P01 | B4: =SUMIFS(Suivi_mensuel!$C:$C,Suivi_mensuel!$A:$A,A4,Suivi_mensuel!$B:$B,$A$1) -> 1 | C4: =SUMIFS(Suivi_mensuel!$D:$D,Suivi_mensuel!$A:$A,A4,Suivi_mensuel!$B:$B,$A$1) -> 0.965 | D4: =+INDEX(Projets!$H:$H,MATCH(A4,Projets!$A:$A,0)) -> 420 | E4: =D4*B4 -> 420 | F4: =D4*C4 -> 405.3 | G4: =SUMIFS(Suivi_mensuel!$E:$E,Suivi_mensuel!$A:$A,A4,Suivi_mensuel!$B:$B,$A$1) -> 416.5 | H4: =+F4/E4 -> 0.965 | I4: =+F4/G4 -> 0.97310924 | J4: =D4/I4 -> 431.60622 | K4: =D4-J4 -> -11.606218 | L4: =+IF(OR(H4<0.85,I4<0.85),"Rouge",IF(OR(H4<0.95,I4<0.95),"Orange","Vert")) -> Vert
A5: P02 | B5: =SUMIFS(Suivi_mensuel!$C:$C,Suivi_mensuel!$A:$A,A5,Suivi_mensuel!$B:$B,$A$1) -> 0.902 | C5: =SUMIFS(Suivi_mensuel!$D:$D,Suivi_mensuel!$A:$A,A5,Suivi_mensuel!$B:$B,$A$1) -> 0.907 | D5: =+INDEX(Projets!$H:$H,MATCH(A5,Projets!$A:$A,0)) -> 260 | E5: =D5*B5 -> 234.52 | F5: =D5*C5 -> 235.82 | G5: =SUMIFS(Suivi_mensuel!$E:$E,Suivi_mensuel!$A:$A,A5,Suivi_mensuel!$B:$B,$A$1) -> 226.6 | H5: =+F5/E5 -> 1.0055432 | I5: =+F5/G5 -> 1.0406884 | J5: =D5/I5 -> 249.83462 | K5: =D5-J5 -> 10.16538 | L5: =+IF(OR(H5<0.85,I5<0.85),"Rouge",IF(OR(H5<0.95,I5<0.95),"Orange","Vert")) -> Vert
A6: P03 | B6: =SUMIFS(Suivi_mensuel!$C:$C,Suivi_mensuel!$A:$A,A6,Suivi_mensuel!$B:$B,$A$1) -> 1 | C6: =SUMIFS(Suivi_mensuel!$D:$D,Suivi_mensuel!$A:$A,A6,Suivi_mensuel!$B:$B,$A$1) -> 0.718 | D6: =+INDEX(Projets!$H:$H,MATCH(A6,Projets!$A:$A,0)) -> 180 | E6: =D6*B6 -> 180 | F6: =D6*C6 -> 129.24 | G6: =SUMIFS(Suivi_mensuel!$E:$E,Suivi_mensuel!$A:$A,A6,Suivi_mensuel!$B:$B,$A$1) -> 160.7 | H6: =+F6/E6 -> 0.718 | I6: =+F6/G6 -> 0.80423149 | J6: =D6/I6 -> 223.81616 | K6: =D6-J6 -> -43.816156 | L6: =+IF(OR(H6<0.85,I6<0.85),"Rouge",IF(OR(H6<0.95,I6<0.95),"Orange","Vert")) -> Rouge
A7: P04 | B7: =SUMIFS(Suivi_mensuel!$C:$C,Suivi_mensuel!$A:$A,A7,Suivi_mensuel!$B:$B,$A$1) -> 0.791 | C7: =SUMIFS(Suivi_mensuel!$D:$D,Suivi_mensuel!$A:$A,A7,Suivi_mensuel!$B:$B,$A$1) -> 0.634 | D7: =+INDEX(Projets!$H:$H,MATCH(A7,Projets!$A:$A,0)) -> 350 | E7: =D7*B7 -> 276.85 | F7: =D7*C7 -> 221.9 | G7: =SUMIFS(Suivi_mensuel!$E:$E,Suivi_mensuel!$A:$A,A7,Suivi_mensuel!$B:$B,$A$1) -> 237.1 | H7: =+F7/E7 -> 0.80151707 | I7: =+F7/G7 -> 0.93589203 | J7: =D7/I7 -> 373.97476 | K7: =D7-J7 -> -23.974763 | L7: =+IF(OR(H7<0.85,I7<0.85),"Rouge",IF(OR(H7<0.95,I7<0.95),"Orange","Vert")) -> Rouge
A8: P05 | B8: =SUMIFS(Suivi_mensuel!$C:$C,Suivi_mensuel!$A:$A,A8,Suivi_mensuel!$B:$B,$A$1) -> 0.946 | C8: =SUMIFS(Suivi_mensuel!$D:$D,Suivi_mensuel!$A:$A,A8,Suivi_mensuel!$B:$B,$A$1) -> 0.972 | D8: =+INDEX(Projets!$H:$H,MATCH(A8,Projets!$A:$A,0)) -> 120 | E8: =D8*B8 -> 113.52 | F8: =D8*C8 -> 116.64 | G8: =SUMIFS(Suivi_mensuel!$E:$E,Suivi_mensuel!$A:$A,A8,Suivi_mensuel!$B:$B,$A$1) -> 109 | H8: =+F8/E8 -> 1.0274841 | I8: =+F8/G8 -> 1.0700917 | J8: =D8/I8 -> 112.13992 | K8: =D8-J8 -> 7.8600823 | L8: =+IF(OR(H8<0.85,I8<0.85),"Rouge",IF(OR(H8<0.95,I8<0.95),"Orange","Vert")) -> Vert
A9: P06 | B9: =SUMIFS(Suivi_mensuel!$C:$C,Suivi_mensuel!$A:$A,A9,Suivi_mensuel!$B:$B,$A$1) -> 0.877 | C9: =SUMIFS(Suivi_mensuel!$D:$D,Suivi_mensuel!$A:$A,A9,Suivi_mensuel!$B:$B,$A$1) -> 0.681 | D9: =+INDEX(Projets!$H:$H,MATCH(A9,Projets!$A:$A,0)) -> 510 | E9: =D9*B9 -> 447.27 | F9: =D9*C9 -> 347.31 | G9: =SUMIFS(Suivi_mensuel!$E:$E,Suivi_mensuel!$A:$A,A9,Suivi_mensuel!$B:$B,$A$1) -> 407.8 | H9: =+F9/E9 -> 0.77651083 | I9: =+F9/G9 -> 0.85166748 | J9: =D9/I9 -> 598.82526 | K9: =D9-J9 -> -88.825257 | L9: =+IF(OR(H9<0.85,I9<0.85),"Rouge",IF(OR(H9<0.95,I9<0.95),"Orange","Vert")) -> Rouge
A10: P07 | B10: =SUMIFS(Suivi_mensuel!$C:$C,Suivi_mensuel!$A:$A,A10,Suivi_mensuel!$B:$B,$A$1) -> 0.584 | C10: =SUMIFS(Suivi_mensuel!$D:$D,Suivi_mensuel!$A:$A,A10,Suivi_mensuel!$B:$B,$A$1) -> 0.549 | D10: =+INDEX(Projets!$H:$H,MATCH(A10,Projets!$A:$A,0)) -> 480 | E10: =D10*B10 -> 280.32 | F10: =D10*C10 -> 263.52 | G10: =SUMIFS(Suivi_mensuel!$E:$E,Suivi_mensuel!$A:$A,A10,Suivi_mensuel!$B:$B,$A$1) -> 264.1 | H10: =+F10/E10 -> 0.94006849 | I10: =+F10/G10 -> 0.99780386 | J10: =D10/I10 -> 481.05647 | K10: =D10-J10 -> -1.0564663 | L10: =+IF(OR(H10<0.85,I10<0.85),"Rouge",IF(OR(H10<0.95,I10<0.95),"Orange","Vert")) -> Orange
A11: P08 | B11: =SUMIFS(Suivi_mensuel!$C:$C,Suivi_mensuel!$A:$A,A11,Suivi_mensuel!$B:$B,$A$1) -> 0.5 | C11: =SUMIFS(Suivi_mensuel!$D:$D,Suivi_mensuel!$A:$A,A11,Suivi_mensuel!$B:$B,$A$1) -> 0.454 | D11: =+INDEX(Projets!$H:$H,MATCH(A11,Projets!$A:$A,0)) -> 300 | E11: =D11*B11 -> 150 | F11: =D11*C11 -> 136.2 | G11: =SUMIFS(Suivi_mensuel!$E:$E,Suivi_mensuel!$A:$A,A11,Suivi_mensuel!$B:$B,$A$1) -> 147.2 | H11: =+F11/E11 -> 0.908 | I11: =+F11/G11 -> 0.92527174 | J11: =D11/I11 -> 324.22907 | K11: =D11-J11 -> -24.229075 | L11: =+IF(OR(H11<0.85,I11<0.85),"Rouge",IF(OR(H11<0.95,I11<0.95),"Orange","Vert")) -> Orange
A12: P09 | B12: =SUMIFS(Suivi_mensuel!$C:$C,Suivi_mensuel!$A:$A,A12,Suivi_mensuel!$B:$B,$A$1) -> 1 | C12: =SUMIFS(Suivi_mensuel!$D:$D,Suivi_mensuel!$A:$A,A12,Suivi_mensuel!$B:$B,$A$1) -> 1 | D12: =+INDEX(Projets!$H:$H,MATCH(A12,Projets!$A:$A,0)) -> 150 | E12: =D12*B12 -> 150 | F12: =D12*C12 -> 150 | G12: =SUMIFS(Suivi_mensuel!$E:$E,Suivi_mensuel!$A:$A,A12,Suivi_mensuel!$B:$B,$A$1) -> 148.2 | H12: =+F12/E12 -> 1 | I12: =+F12/G12 -> 1.0121457 | J12: =D12/I12 -> 148.2 | K12: =D12-J12 -> 1.8 | L12: =+IF(OR(H12<0.85,I12<0.85),"Rouge",IF(OR(H12<0.95,I12<0.95),"Orange","Vert")) -> Vert
A13: P10 | B13: =SUMIFS(Suivi_mensuel!$C:$C,Suivi_mensuel!$A:$A,A13,Suivi_mensuel!$B:$B,$A$1) -> 0.676 | C13: =SUMIFS(Suivi_mensuel!$D:$D,Suivi_mensuel!$A:$A,A13,Suivi_mensuel!$B:$B,$A$1) -> 0.683 | D13: =+INDEX(Projets!$H:$H,MATCH(A13,Projets!$A:$A,0)) -> 90 | E13: =D13*B13 -> 60.84 | F13: =D13*C13 -> 61.47 | G13: =SUMIFS(Suivi_mensuel!$E:$E,Suivi_mensuel!$A:$A,A13,Suivi_mensuel!$B:$B,$A$1) -> 60.8 | H13: =+F13/E13 -> 1.010355 | I13: =+F13/G13 -> 1.0110197 | J13: =D13/I13 -> 89.019034 | K13: =D13-J13 -> 0.98096633 | L13: =+IF(OR(H13<0.85,I13<0.85),"Rouge",IF(OR(H13<0.95,I13<0.95),"Orange","Vert")) -> Vert

Sheet Dashboard
A1: PORTEFEUILLE PRODUITS DIGITAUX Situation au 31/08/2026 - Montants en M FCFA
B3: Produits en rouge | C3: Produits en orange | D3: Produits en vert | E3: Budget Total | F3: Coût final estimé | H3: Dépassement attendu
B4: =+COUNTIF(Calcul!$L$4:$L$13,"Rouge") -> 3 | C4: =+COUNTIF(Calcul!$L$4:$L$13,"orange") -> 2 | D4: =+COUNTIF(Calcul!$L$4:$L$13,"vert") -> 5 | E4: =SUM(Calcul!$D$4:$D$13) -> 2860 | F4: =SUM(Calcul!$J$4:$J$13) -> 3032.7015 | H4: =SUM(Calcul!$K$4:$K$13) -> -172.70151
B29: Les trois produits à débloquer en priorité
B30: Rang | C30: Produit | D30: Statut | E30: SPI | F30: CPI | G30: Dépassement attendu | H30: Actions à arbitrer
B31: 1 | C31: P06 - Migration du CRM | D31: Rouge | E31: 0.77651083 | F31: 0.85166748 | G31: -88.825257 | H31: Nettoyage des données clients avant bascule
B32: 2 | C32: P03 - Programme de fidelité | D32: Rouge | E32: 0.718 | F32: 0.80423149 | G32: -43.816156 | H32: Relancer les partenaires , plafonner les récompenses
B33: 3 | C33: P08 - Marketplace partenaires | D33: Orange | E33: 0.908 | F33: 0.92527174 | G33: -24.229075 | H33: Finaliser le contrat type partenaires
